pollination/honeybee_vtk/__init__.py
pollination/honeybee_vtk/config.py
pollination/honeybee_vtk/export.py
pollination/honeybee_vtk/post_process.py
pollination/honeybee_vtk/translate.py
pollination_honeybee_vtk-0.4.12.dist-info/LICENSE
pollination_honeybee_vtk-0.4.12.dist-info/METADATA
pollination_honeybee_vtk-0.4.12.dist-info/WHEEL
pollination_honeybee_vtk-0.4.12.dist-info/top_level.txt
pollination_honeybee_vtk-0.4.12.dist-info/RECORD
