Metadata-Version: 2.1
Name: pollination-honeybee-vtk
Version: 0.4.12
Summary: Honeybee vtk plugin for Pollination.
Home-page: https://github.com/pollination/honeybee-vtk
Author: ladybug-tools
Author-email: info@ladybug.tools
Maintainer: Devang, ladybug-tools
Maintainer-email: devang@ladybug.tools, info@ladybug.tools
License: PolyForm Shield License 1.0.0, https://polyformproject.org/wp-content/uploads/2020/06/PolyForm-Shield-1.0.0.txt
Project-URL: icon, https://raw.githubusercontent.com/pollination/honeybee-vtk/master/assets/logo/vtk.png
Project-URL: docker, https://hub.docker.com/r/ladybugtools/honeybee-vtk
Keywords: honeybee,vtk,hbjson,ladybug-tools
License-File: LICENSE
Requires-Dist: pollination-dsl (>=0.14.1)
Requires-Dist: honeybee-vtk (>=0.39)
